skoufas_dbf_reader/__init__.py
skoufas_dbf_reader/correction_data.py
skoufas_dbf_reader/dbf_to_yaml.py
skoufas_dbf_reader/field_extractors.py
skoufas_dbf_reader/generate_reports.py
skoufas_dbf_reader/utilities.py
skoufas_dbf_reader/data/author_corrections.yml
skoufas_dbf_reader/data/converted_entries.yml
skoufas_dbf_reader/data/editor_corrections.yml
skoufas_dbf_reader/data/entries.yml
skoufas_dbf_reader/data/field04_corrections.yml
skoufas_dbf_reader/data/field05_corrections.yml
skoufas_dbf_reader/data/field06_corrections.yml
skoufas_dbf_reader/data/field07_corrections.yml
skoufas_dbf_reader/data/field08_corrections.yml
skoufas_dbf_reader/data/field09_corrections.yml
skoufas_dbf_reader/data/field10_corrections.yml
skoufas_dbf_reader/data/field11_corrections.yml
skoufas_dbf_reader/data/field16_corrections.yml
skoufas_dbf_reader/data/field17_corrections.yml
skoufas_dbf_reader/data/field18_corrections.yml
skoufas_dbf_reader/data/field19_corrections.yml
skoufas_dbf_reader/data/field20_corrections.yml
skoufas_dbf_reader/data/field30_corrections.yml
skoufas_dbf_reader/data/first_names.yml
skoufas_dbf_reader/data/language_codes.yml
skoufas_dbf_reader/data/topic_replacements.yml
skoufas_dbf_reader/data/translator_corrections.yml
skoufas_dbf_reader-2025.12.28.dist-info/entry_points.txt
skoufas_dbf_reader-2025.12.28.dist-info/licenses/LICENSE
skoufas_dbf_reader-2025.12.28.dist-info/WHEEL
skoufas_dbf_reader-2025.12.28.dist-info/METADATA
skoufas_dbf_reader-2025.12.28.dist-info/RECORD
