Metadata-Version: 2.4
Name: skoufas-dbf-reader
Version: 2025.12.28
Summary: Library for reading legacy DBF file with library data
Author-email: Claudio Bantaloukas <rockreamer@gmail.com>
Requires-Python: >=3.10
Classifier: Development Status :: 3 - Alpha
Classifier: Intended Audience :: Other Audience
Classifier: License :: OSI Approved :: GNU Affero General Public License v3
Classifier: Programming Language :: Python :: 3 :: Only
Classifier: Programming Language :: Python :: 3.10
Classifier: Programming Language :: Python :: 3.12
License-File: LICENSE
Requires-Dist: dbfread==2.0.7
Requires-Dist: snakemd==2.4.0
Requires-Dist: PyYAML>=6.0
Requires-Dist: bandit[toml]==1.9.2 ; extra == "test"
Requires-Dist: ruff ; extra == "test"
Requires-Dist: check-manifest==0.51 ; extra == "test"
Requires-Dist: mypy ; extra == "test"
Requires-Dist: pre-commit==4.5.1 ; extra == "test"
Requires-Dist: pylint==4.0.4 ; extra == "test"
Requires-Dist: pylint_junit ; extra == "test"
Requires-Dist: pytest-cov==7.0.0 ; extra == "test"
Requires-Dist: pytest-mock ; extra == "test"
Requires-Dist: pytest-runner ; extra == "test"
Requires-Dist: pytest==9.0.2 ; extra == "test"
Requires-Dist: pytest-github-actions-annotate-failures ; extra == "test"
Requires-Dist: shellcheck-py==0.11.0.1 ; extra == "test"
Project-URL: Documentation, https://github.com/skoufas/skoufas-dbf-reader#readme
Project-URL: Source, https://github.com/skoufas/skoufas-dbf-reader
Project-URL: Tracker, https://github.com/skoufas/skoufas-dbf-reader/issues
Provides-Extra: test
